cadvectorgraphics/__init__.py
cadvectorgraphics/compose/__init__.py
cadvectorgraphics/compose/compose.py
cadvectorgraphics/compose/components/__init__.py
cadvectorgraphics/compose/components/bind.py
cadvectorgraphics/compose/components/illuminate.py
cadvectorgraphics/compose/components/view.py
cadvectorgraphics/compose/components/representation/__init__.py
cadvectorgraphics/compose/components/representation/cad.py
cadvectorgraphics/compose/components/representation/material.py
cadvectorgraphics/compose/components/representation/mesh.py
cadvectorgraphics/illustrate/__init__.py
cadvectorgraphics/illustrate/illustrate.py
cadvectorgraphics/illustrate/components/__init__.py
cadvectorgraphics/illustrate/components/style.py
cadvectorgraphics/illustrate/components/svg.py
cadvectorgraphics/render/__init__.py
cadvectorgraphics/render/render.py
cadvectorgraphics/render/components/__init__.py
cadvectorgraphics/render/components/geometry.py
cadvectorgraphics/render/components/project.py
cadvectorgraphics/util/__init__.py
cadvectorgraphics/util/color.py
cadvectorgraphics/util/geometry.py
cadvectorgraphics-1.0.0.dist-info/LICENSE
cadvectorgraphics-1.0.0.dist-info/METADATA
cadvectorgraphics-1.0.0.dist-info/WHEEL
cadvectorgraphics-1.0.0.dist-info/top_level.txt
cadvectorgraphics-1.0.0.dist-info/RECORD
