Metadata-Version: 2.1
Name: cadvectorgraphics
Version: 1.0.0
Summary: A python package for generating beautiful SVG from CAD data
Author-email: Dennis Schulz <dennisschulz2000@gmail.com>
Project-URL: Repository, https://github.com/sxhulzenstein/CADToVectorGraphics
Classifier: Programming Language :: Python :: 3
Classifier: Operating System :: OS Independent
Requires-Python: >=3.8
License-File: LICENSE
